fwdatafile/__init__.py
fwdatafile/errors.py
fwdatafile/registro.py
fwdatafile/tipos.py
python3_fwfile-0.0.1.dist-info/LICENSE
python3_fwfile-0.0.1.dist-info/METADATA
python3_fwfile-0.0.1.dist-info/WHEEL
python3_fwfile-0.0.1.dist-info/top_level.txt
python3_fwfile-0.0.1.dist-info/RECORD
