Metadata-Version: 2.1
Name: python3-fwfile
Version: 0.0.1
Summary: Lib para gerar arquivo TXT de tamanho fixo
Home-page: https://www.opussystem.com.br
Author: OpusSystem
Author-email: suporte@opussystem.com.br
License: MIT
Download-URL: https://github.com/Trust-Code/python-cnab
Keywords: fixed,width,text
Platform: any
Classifier: Development Status :: 3 - Alpha
Classifier: Environment :: Plugins
Classifier: Intended Audience :: Developers
Classifier: Operating System :: OS Independent
Classifier: Programming Language :: Python
Classifier: Programming Language :: Python :: 3.10
Classifier: Programming Language :: Python :: 3.9
Classifier: Programming Language :: Python :: 3.8
Classifier: Programming Language :: Python :: 3.7
Classifier: Programming Language :: Python :: 3.6
Classifier: Programming Language :: Python :: 3.5
Classifier: Programming Language :: Python :: 3.4
Classifier: Topic :: Software Development :: Libraries :: Python Modules
License-File: LICENSE
Requires-Dist: setuptools-git
